[1,["7fep/m6XNKK6F3JYbua1ti@6c48a"],["_textureSource"],["cc.SpriteFrame"],0,[{"name":"ui_5","rect":{"x":36,"y":13,"width":220,"height":51},"offset":{"x":2,"y":-1},"originalSize":{"width":288,"height":75},"rotated":false,"capInsets":[0,0,0,0],"vertices":{"rawPosition":[-110,-25.5,0,110,-25.5,0,-110,25.5,0,110,25.5,0],"indexes":[0,1,2,2,1,3],"uv":[36,62,256,62,36,11,256,11],"nuv":[0.125,0.14666666666666667,0.8888888888888888,0.14666666666666667,0.125,0.8266666666666667,0.8888888888888888,0.8266666666666667],"minPos":{"x":-110,"y":-25.5,"z":0},"maxPos":{"x":110,"y":25.5,"z":0}},"packable":true,"pixelsToUnit":100,"pivot":{"x":0.5,"y":0.5},"meshType":0}],[0],0,[0],[0],[0]]
